{
    "Server": {
        "NumberOfServer": 1, 
        "ServerInfo": [
            {
                "ServerID": "wmnet202.cs.nthu.edu.tw", 
                "CoreInfo": {
                    "NumberOfCore": 5, 
                    "Load": 0.5077282219285715
                }, 
                "MemInfo": {
                    "SizeOfMem": 16258772992, 
                    "CurrUsage": 12835213312, 
                    "MajorPageFaultCumulative": 642, 
                    "PageFaultCumulative": 10813329, 
                    "WorkingSet": 9845112832
                }, 
                "DiskInfo": {
                    "FilesystemLimit": 53660876800, 
                    "FilesystemUsage": 13221122048
                }, 
                "NetworkInfo": {
                    "ReceivedCumulativeBytes": 3262430214224, 
                    "ReceivedErrorsCumulativeCounts": 0, 
                    "SentCumulativeBytes": 292004608246, 
                    "SentErrorsCumulativeCount": 0
                }, 
                "UpTimemsCumulative": 6277517560
            }
        ]
    }, 
    "Application": [
        {
            "ApplicationID": "docker-registry", 
            "AvgResponseTime": 2.09, 
            "SLA": "Not Define", 
            "pod": {
                "NumberOfPod": 1, 
                "PodInfo": [
                    {
                        "PodID": "docker-registry-1-9kddd", 
                        "nodeName": "wmnet202.cs.nthu.edu.tw", 
                        "Contents": {
                            "CpuLimit": -1, 
                            "CpuUsage": 0.3840776, 
                            "MemoryLimit": -1, 
                            "MemoryUsage": 19374080, 
                            "MemoryMajorPageFaultsCumulative": 24, 
                            "MemoryPageFaultsCumulative": 129367, 
                            "MemoryWorkingSet": 7049216, 
                            "UpTimemsCumulative": 6277474657
                        }
                    }
                ]
            }
        }, 
        {
            "ApplicationID": "kubernetes", 
            "AvgResponseTime": "Not Define", 
            "SLA": "Not Define", 
            "pod": {
                "NumberOfPod": 0, 
                "PodInfo": []
            }
        }, 
        {
            "ApplicationID": "router", 
            "AvgResponseTime": "Not Define", 
            "SLA": "Not Define", 
            "pod": {
                "NumberOfPod": 1, 
                "PodInfo": [
                    {
                        "PodID": "router-1-titpp", 
                        "nodeName": "wmnet202.cs.nthu.edu.tw", 
                        "Contents": {
                            "CpuLimit": -1, 
                            "CpuUsage": 2.4125237142857148, 
                            "MemoryLimit": -1, 
                            "MemoryUsage": 114880512, 
                            "MemoryMajorPageFaultsCumulative": 101, 
                            "MemoryPageFaultsCumulative": 1981051, 
                            "MemoryWorkingSet": 24903680, 
                            "UpTimemsCumulative": 57097119
                        }
                    }
                ]
            }
        }, 
        {
            "ApplicationID": "heapster", 
            "AvgResponseTime": 2.98, 
            "SLA": "Not Define", 
            "pod": {
                "NumberOfPod": 1, 
                "PodInfo": [
                    {
                        "PodID": "heapster-6ymhq", 
                        "nodeName": "wmnet202.cs.nthu.edu.tw", 
                        "Contents": {
                            "CpuLimit": 199, 
                            "CpuUsage": 7.3144405882352945, 
                            "MemoryLimit": 314572800, 
                            "MemoryUsage": 49451008, 
                            "MemoryMajorPageFaultsCumulative": 27, 
                            "MemoryPageFaultsCumulative": 1399837, 
                            "MemoryWorkingSet": 30089216, 
                            "UpTimemsCumulative": 5932592051
                        }
                    }
                ]
            }
        }, 
        {
            "ApplicationID": "influxdb-api", 
            "AvgResponseTime": "Not Define", 
            "SLA": "Not Define", 
            "pod": {
                "NumberOfPod": 1, 
                "PodInfo": [
                    {
                        "PodID": "influxdb-grafana-8xzha", 
                        "nodeName": "wmnet202.cs.nthu.edu.tw", 
                        "Contents": {
                            "CpuLimit": -2, 
                            "CpuUsage": 36.66728287777778, 
                            "MemoryLimit": -2, 
                            "MemoryUsage": 3147001856, 
                            "MemoryMajorPageFaultsCumulative": 103, 
                            "MemoryPageFaultsCumulative": 10017553, 
                            "MemoryWorkingSet": 3060494336, 
                            "UpTimemsCumulative": 5933020451
                        }
                    }
                ]
            }
        }, 
        {
            "ApplicationID": "monitoring-grafana", 
            "AvgResponseTime": 18.22, 
            "SLA": "Not Define", 
            "pod": {
                "NumberOfPod": 1, 
                "PodInfo": [
                    {
                        "PodID": "influxdb-grafana-8xzha", 
                        "nodeName": "wmnet202.cs.nthu.edu.tw", 
                        "Contents": {
                            "CpuLimit": -2, 
                            "CpuUsage": 36.66728287777778, 
                            "MemoryLimit": -2, 
                            "MemoryUsage": 3147001856, 
                            "MemoryMajorPageFaultsCumulative": 103, 
                            "MemoryPageFaultsCumulative": 10017553, 
                            "MemoryWorkingSet": 3060494336, 
                            "UpTimemsCumulative": 5933020451
                        }
                    }
                ]
            }
        }, 
        {
            "ApplicationID": "monitoring-influxdb", 
            "AvgResponseTime": 19.13, 
            "SLA": "Not Define", 
            "pod": {
                "NumberOfPod": 1, 
                "PodInfo": [
                    {
                        "PodID": "influxdb-grafana-8xzha", 
                        "nodeName": "wmnet202.cs.nthu.edu.tw", 
                        "Contents": {
                            "CpuLimit": -2, 
                            "CpuUsage": 36.66728287777778, 
                            "MemoryLimit": -2, 
                            "MemoryUsage": 3147001856, 
                            "MemoryMajorPageFaultsCumulative": 103, 
                            "MemoryPageFaultsCumulative": 10017553, 
                            "MemoryWorkingSet": 3060494336, 
                            "UpTimemsCumulative": 5933020451
                        }
                    }
                ]
            }
        }, 
        {
            "ApplicationID": "experiment-app", 
            "AvgResponseTime": 127.02, 
            "SLA": "Not Define", 
            "pod": {
                "NumberOfPod": 1, 
                "PodInfo": [
                    {
                        "PodID": "experiment-app-1-35rj1", 
                        "nodeName": "wmnet202.cs.nthu.edu.tw", 
                        "Contents": {
                            "CpuLimit": 500, 
                            "CpuUsage": 27.663231684210526, 
                            "MemoryLimit": 314572800, 
                            "MemoryUsage": 28241920, 
                            "MemoryMajorPageFaultsCumulative": 87, 
                            "MemoryPageFaultsCumulative": 906215770, 
                            "MemoryWorkingSet": 10596352, 
                            "UpTimemsCumulative": 3348786358
                        }
                    }
                ]
            }
        }, 
        {
            "ApplicationID": "ticket-monster", 
            "AvgResponseTime": 10.34, 
            "SLA": "Not Define", 
            "pod": {
                "NumberOfPod": 1, 
                "PodInfo": [
                    {
                        "PodID": "ticket-monster-m9hc7", 
                        "nodeName": "wmnet202.cs.nthu.edu.tw", 
                        "Contents": {
                            "CpuLimit": 500, 
                            "CpuUsage": 11.272491533333334, 
                            "MemoryLimit": 1610612736, 
                            "MemoryUsage": 1046466560, 
                            "MemoryMajorPageFaultsCumulative": 283, 
                            "MemoryPageFaultsCumulative": 219533, 
                            "MemoryWorkingSet": 876687360, 
                            "UpTimemsCumulative": 172676405
                        }
                    }
                ]
            }
        }
    ], 
    "Lastest Update time": "17:50:10"
}